<Ouvertures Type="Porte entiere">
  <Ouverture>
    <Longueur>0.4848</Longueur>
    <Hauteur>0.4776</Hauteur>
    <Reponse>Oui</Reponse>
    <Temps_de_reponse>2.271</Temps_de_reponse>
  </Ouverture>
  <Ouverture>
    <Longueur>0.48</Longueur>
    <Hauteur>0.4824</Hauteur>
    <Reponse>Oui</Reponse>
    <Temps_de_reponse>0.116</Temps_de_reponse>
  </Ouverture>
  <Ouverture>
    <Longueur>0.4752</Longueur>
    <Hauteur>0.4776</Hauteur>
    <Reponse>Oui</Reponse>
    <Temps_de_reponse>0.109</Temps_de_reponse>
  </Ouverture>
  <Ouverture>
    <Longueur>0.48</Longueur>
    <Hauteur>0.4776</Hauteur>
    <Reponse>Oui</Reponse>
    <Temps_de_reponse>0.116</Temps_de_reponse>
  </Ouverture>
  <Ouverture>
    <Longueur>0.4752</Longueur>
    <Hauteur>0.4824</Hauteur>
    <Reponse>Oui</Reponse>
    <Temps_de_reponse>0.14</Temps_de_reponse>
  </Ouverture>
  <Ouverture>
    <Longueur>0.4848</Longueur>
    <Hauteur>0.4824</Hauteur>
    <Reponse>Oui</Reponse>
    <Temps_de_reponse>0.479</Temps_de_reponse>
  </Ouverture>
</Ouvertures>